pyrander/__init__.py
pyrander/core.py
pyrander/version.py
pyrander-0.2.0a0.dist-info/LICENSE.txt
pyrander-0.2.0a0.dist-info/METADATA
pyrander-0.2.0a0.dist-info/WHEEL
pyrander-0.2.0a0.dist-info/top_level.txt
pyrander-0.2.0a0.dist-info/RECORD
